napari_automatic_range/__init__.py
napari_automatic_range/_reader.py
napari_automatic_range/_sample_data.py
napari_automatic_range/_version.py
napari_automatic_range/_widget.py
napari_automatic_range/_writer.py
napari_automatic_range/napari.yaml
napari_automatic_range/_tests/__init__.py
napari_automatic_range/_tests/test_reader.py
napari_automatic_range/_tests/test_sample_data.py
napari_automatic_range/_tests/test_writer.py
napari_automatic_range-0.1.4.dist-info/licenses/LICENSE
napari_automatic_range-0.1.4.dist-info/METADATA
napari_automatic_range-0.1.4.dist-info/WHEEL
napari_automatic_range-0.1.4.dist-info/entry_points.txt
napari_automatic_range-0.1.4.dist-info/top_level.txt
napari_automatic_range-0.1.4.dist-info/RECORD
