Metadata-Version: 2.4
Name: napari-automatic-range
Version: 0.1.4
Summary: An open‑source, reproducible intensity‑scaling method that leverages the nuclear signal as an anchor to calibrate per‑channel contrast. 
Author: Pacôme Prompsy
Author-email: pacome.prompsy@unil.ch
License: 
Project-URL: Bug Tracker, https://github.com/pacomito/napari-automatic-range/issues
Project-URL: Documentation, https://github.com/pacomito/napari-automatic-range#README.md
Project-URL: Source Code, https://github.com/pacomito/napari-automatic-range
Project-URL: User Support, https://github.com/pacomito/napari-automatic-range/issues
Classifier: Development Status :: 2 - Pre-Alpha
Classifier: Framework :: napari
Classifier: Intended Audience :: Developers
Classifier: License :: OSI Approved :: GNU General Public License v3 (GPLv3)
Classifier: Operating System :: OS Independent
Classifier: Programming Language :: Python
Classifier: Programming Language :: Python :: 3
Classifier: Programming Language :: Python :: 3 :: Only
Classifier: Programming Language :: Python :: 3.10
Classifier: Programming Language :: Python :: 3.11
Classifier: Programming Language :: Python :: 3.12
Classifier: Programming Language :: Python :: 3.13
Classifier: Topic :: Scientific/Engineering :: Image Processing
Requires-Python: >=3.10
License-File: LICENSE
Requires-Dist: numpy
Requires-Dist: magicgui
Requires-Dist: qtpy
Requires-Dist: scikit-image
Requires-Dist: AutomaticRange
Provides-Extra: all
Requires-Dist: napari[all]; extra == "all"
Provides-Extra: testing
Requires-Dist: tox; extra == "testing"
Requires-Dist: pytest; extra == "testing"
Requires-Dist: pytest-cov; extra == "testing"
Requires-Dist: pytest-qt; extra == "testing"
Requires-Dist: napari[qt]; extra == "testing"
Dynamic: license-file
